oldvis_dataset/__init__.py
oldvis_dataset/bib.py
oldvis_dataset/images.py
oldvis_dataset/metadata.py
oldvis_dataset-0.1.1.dist-info/LICENSE
oldvis_dataset-0.1.1.dist-info/METADATA
oldvis_dataset-0.1.1.dist-info/WHEEL
oldvis_dataset-0.1.1.dist-info/RECORD
