Metadata-Version: 2.1
Name: oldvis-dataset
Version: 0.1.1
Summary: 
Author: Yu Zhang
Author-email: yuzhang94@outlook.com
Requires-Python: >=3.10,<4.0
Classifier: Programming Language :: Python :: 3
Classifier: Programming Language :: Python :: 3.10
Classifier: Programming Language :: Python :: 3.11
Requires-Dist: bibtexparser (>=2.0.0b2,<3.0.0)
Requires-Dist: langcodes (>=3.3.0,<4.0.0)
Requires-Dist: language-data (>=1.1,<2.0)
Requires-Dist: requests (>=2.31.0,<3.0.0)
Requires-Dist: tqdm (>=4.65.0,<5.0.0)
